validate_aws_sns_message/__init__.py
validate_aws_sns_message-0.9.0.dist-info/LICENCE
validate_aws_sns_message-0.9.0.dist-info/METADATA
validate_aws_sns_message-0.9.0.dist-info/WHEEL
validate_aws_sns_message-0.9.0.dist-info/top_level.txt
validate_aws_sns_message-0.9.0.dist-info/RECORD
