Metadata-Version: 2.1
Name: validate-aws-sns-message
Version: 0.9.0
Summary: Validate integrity of Amazon SNS messages (Refined)
Home-page: https://github.com/kenichi-ogawa-1988/validate_aws_sns_message
Author: Ken'ichi Ogawa
Author-email: kenichi@ogwk.net
License: UNKNOWN
Platform: UNKNOWN
Classifier: Development Status :: 4 - Beta
Classifier: Intended Audience :: Developers
Classifier: Topic :: Software Development
Classifier: License :: OSI Approved :: MIT License
Classifier: Programming Language :: Python :: 2
Classifier: Programming Language :: Python :: 2.7
Classifier: Programming Language :: Python :: 3
Classifier: Programming Language :: Python :: 3.3
Classifier: Programming Language :: Python :: 3.4
